<?xml version="1.0" encoding="UTF-8"?>
<dic>
	<p c="ב" a="b">
		<n v="ב" id="aa">176</n>
		<n v="בְ" id="ab1">1566</n>
		<n v="בְֽ" id="ab2">4</n>
		<n v="בִ" id="ac1">337</n>
		<n v="בִֽ" id="ac2">49</n>
		<n v="בֵ" id="ad1">9</n>
		<n v="בֵֽ" id="ad2">5</n>
		<n v="בֶ" id="ae1">32</n>
		<n v="בֶֽ" id="ae2">7</n>
		<n v="בַ" id="af1">678</n>
		<n v="בַֽ" id="af2">25</n>
		<n v="בָ" id="ag1">441</n>
		<n v="בָֽ" id="ag2">74</n>
		<n v="בּ" id="ah">190</n>
		<n v="בְּ" id="ai1">6609</n>
		<n v="בְּֽ" id="ai2">54</n>
		<n v="בִּ" id="aj1">1204</n>
		<n v="בִּֽ" id="aj2">106</n>
		<n v="בֵּ" id="ak1">61</n>
		<n v="בֵּֽ" id="ak2">18</n>
		<n v="בֶּ" id="al1">113</n>
		<n v="בֶּֽ" id="al2">24</n>
		<n v="בַּ" id="am1">2591</n>
		<n v="בַּֽ" id="am2">141</n>
		<n v="בָּ" id="an1">1083</n>
		<n v="בָּֽ" id="an2">160</n>
		<n v="בּֽ" id="ao">59</n>
		<n v="בַּֽ" id="ap">11</n>
		<n v="בָּֽ" id="aq">4</n>
		<n v="בֽ" id="ar">27</n>
		<n v="בָֽ" id="as">1</n>
	</p>
	<p c="ה" a="d">
		<n v="ה" id="ba">80</n>
		<n v="הְֽ" id="bb">1</n>
		<n v="הֲ" id="bc">1</n>
		<n v="הֳ" id="bd">1</n>
		<n v="הֶ" id="be">288</n>
		<n v="הֶֽ" id="bf">111</n>
		<n v="הַ" id="bg">16285</n>
		<n v="הַֽ" id="bh">591</n>
		<n v="הַׄ" id="bi">1</n>
		<n v="הָ" id="bj">5893</n>
		<n v="הָֽ" id="bk">645</n>
		<n v="הֶֽ" id="bl">5</n>
		<n v="הַֽ" id="bm">64</n>
		<n v="הָֽ" id="bn">99</n>
	</p>
	<p c="ה" a="i">
		<n v="הְֽ" id="ca">2</n>
		<n v="הֲ" id="cb">529</n>
		<n v="הֲֽ" id="cc">2</n>
		<n v="הֶ" id="cd">2</n>
		<n v="הֶֽ" id="ce">2</n>
		<n v="הַ" id="cf">85</n>
		<n v="הַֽ" id="cg">19</n>
		<n v="הֲֽ" id="ch">1</n>
		<n v="הַֽ" id="ci">2</n>
		<n v="הָֽ" id="cj">1</n>
		<n v="הֲ‍ֽ" id="ck">13</n>
	</p>
	<p c="ו" a="c">
		<n v="ו" id="da">273</n>
		<n v="וְ" id="db">24159</n>
		<n v="וְֽ" id="dc">293</n>
		<n v="וְׄ" id="dd">1</n>
		<n v="וֲ" id="de">1</n>
		<n v="וִ" id="df">245</n>
		<n v="וִֽ" id="dg">223</n>
		<n v="וֵ" id="dh">20</n>
		<n v="וֵֽ" id="di">8</n>
		<n v="וֶ" id="dj">96</n>
		<n v="וֶֽ" id="dk">19</n>
		<n v="וַ" id="dl">14962</n>
		<n v="וַֽ" id="dm">980</n>
		<n v="וַׄ" id="dn">1</n>
		<n v="וָ" id="do">1223</n>
		<n v="וָֽ" id="dp">87</n>
		<n v="וּ" id="dq">8226</n>
		<n v="וִּ" id="dr">2</n>
		<n v="וּֽ" id="ds">269</n>
		<n v="וּׄ" id="dt">1</n>
		<n v="וְֽ" id="du">9</n>
		<n v="וִֽ" id="dv">1</n>
		<n v="וֵֽ" id="dw">4</n>
		<n v="וֶֽ" id="dx">10</n>
		<n v="וַֽ" id="dy">157</n>
		<n v="וָֽ" id="dz">5</n>
	</p>
	<p c="כ" a="k">
		<n v="כ" id="ea">7</n>
		<n v="כְ" id="eb">218</n>
		<n v="כִ" id="ec">57</n>
		<n v="כֶ" id="ed">8</n>
		<n v="כַ" id="ef">132</n>
		<n v="כַֽ" id="eg">6</n>
		<n v="כָ" id="eh">50</n>
		<n v="כְּ" id="ei">1040</n>
		<n v="כְּֽ" id="ej">23</n>
		<n v="כִּ" id="ek">306</n>
		<n v="כִּֽ" id="el">3</n>
		<n v="כֵּ" id="em">1</n>
		<n v="כֵּֽ" id="en">4</n>
		<n v="כֶּ" id="eo">13</n>
		<n v="כֶּֽ" id="ep">10</n>
		<n v="כַּ" id="eq">894</n>
		<n v="כַּֽ" id="er">36</n>
		<n v="כָּ" id="es">136</n>
		<n v="כָּֽ" id="et">11</n>
		<n v="כַּֽ" id="eu">16</n>
		<n v="כָּֽ" id="ev">1</n>
	</p>
	<p c="ל" a="l">
		<n v="ל" id="fa">1002</n>
		<n v="לְ" id="fb1">8099</n>
		<n v="לְֽ" id="fb2">52</n>
		<n v="לְׄ" id="fb3">1</n>
		<n v="לֲ" id="fc">4</n>
		<n v="לִ" id="fd1">3037</n>
		<n v="לִֽ" id="fd2">200</n>
		<n v="לֵ" id="fe1">963</n>
		<n v="לֵֽ" id="fe2">46</n>
		<n v="לֶ" id="ff1">130</n>
		<n v="לֶֽ" id="ff2">20</n>
		<n v="לַ" id="fg1">2488</n>
		<n v="לַֽ" id="fg2">412</n>
		<n v="לָ" id="fh1">3348</n>
		<n v="לָֽ" id="fh2">236</n>
		<n v="לָׄ" id="fh3">1</n>
		<n v="לּ" id="fi">82</n>
		<n v="לְּ" id="fj">131</n>
		<n v="לִּ" id="fl1">181</n>
		<n v="לִּֽ" id="fl2">8</n>
		<n v="לֵּ" id="fm">77</n>
		<n v="לֶּ" id="fn">1</n>
		<n v="לַּ" id="fo">3</n>
		<n v="לָּ" id="fp1">111</n>
		<n v="לָּֽ" id="fp2">29</n>
		<n v="לּֽ" id="fq1">13</n>
		<n v="לֽ" id="fq2">128</n>
		<n v="לְֽ" id="fr">1</n>
		<n v="לִֽ" id="fs">1</n>
		<n v="לֵֽ" id="ft">9</n>
		<n v="לֶֽ" id="fu">2</n>
		<n v="לַֽ" id="fv">33</n>
		<n v="לָֽ" id="fw">2</n>
		<n v="לִֽֿ" id="fx">1</n>
	</p>
	<p c="מ" a="m">
		<n v="מ" id="ga">23</n>
		<n v="מְ" id="gb">1</n>
		<n v="מִ" id="gc">4050</n>
		<n v="מִֽ" id="gd">137</n>
		<n v="מֵ" id="ge">1852</n>
		<n v="מֵֽ" id="gf">334</n>
		<n v="מֶ" id="gg">2</n>
		<n v="מֶֽ" id="gh">3</n>
		<n v="מַ" id="gi">3</n>
		<n v="מִּ" id="gj">2</n>
		<n v="מֵּ" id="gk">3</n>
		<n v="מֵֽ" id="gl">9</n>
	</p>
	<p c="ש" a="s">
		<n v="ש" id="ha">3</n>
		<n v="שְׁ" id="hb">1</n>
		<n v="שֶׁ" id="hc">117</n>
		<n v="שֶֽׁ" id="hd">9</n>
		<n v="שַׁ" id="he">5</n>
		<n v="שָׁ" id="hf">1</n>
		<n v="שֶּׁ" id="hg">3</n>
		<n v="שֶּֽׁ" id="hh">3</n>
	</p>
	<s c="א">
		<n v="א" id="ia">826</n>
	</s>
	<s c="אה">
		<n v="אָה" id="ib">2</n>
	</s>
	<s c="די">
		<n v="דִי" id="j">2</n>
	</s>
	<s c="ה">
		<n v="ה" id="ka1">1708</n>
		<n v="הָ" id="ka2">1293</n>
		<n v="הּ" id="ka3">1980</n>
		<n v="הָּ" id="ka4">2</n>
		<n v="הֿ" id="ka5">2</n>
	</s>
	<s c="הא">
		<n v="הָא" id="kb1">1</n>
		<n v="הא" id="kb2">1</n>
	</s>
	<s c="הו">
		<n v="הֽוּ" id="kc1">4</n>
		<n v="הׄוּׄ" id="kc2">1</n>
		<n v="הו" id="kc3">4</n>
		<n v="הוּ" id="kc4">1060</n>
	</s>
	<s c="הוא">
		<n v="הוא" id="kd">1</n>
	</s>
	<s c="הום">
		<n v="הוֹם" id="ke">1</n>
	</s>
	<s c="הון">
		<n v="הֽוֹן" id="kf1">6</n>
		<n v="הוֹן" id="kf2">45</n>
		<n v="הון" id="kf3">10</n>
	</s>
	<s c="הי">
		<n v="הִי" id="kg">76</n>
	</s>
	<s c="הין">
		<n v="הֵין" id="kh">6</n>
	</s>
	<s c="הם">
		<n v="הֶֽם" id="ki1">410</n>
		<n v="הֶם" id="ki2">2357</n>
		<n v="הַם" id="ki3">1</n>
		<n v="הֹֽם" id="ki4">3</n>
		<n v="הֹם" id="ki5">8</n>
		<n v="הֶּם" id="ki6">1</n>
		<n v="הֶֽם" id="ki7">1</n>
		<n v="הם" id="ki8">13</n>
	</s>
	<s c="המה">
		<n v="הֵמָה" id="kj">1</n>
	</s>
	<s c="הן">
		<n v="הֵן" id="kl1">8</n>
		<n v="הֶֽן" id="kl2">55</n>
		<n v="הֶן" id="kl3">105</n>
	</s>
	<s c="הנה">
		<n v="הְנָה" id="km1">2</n>
		<n v="הֶֽנָה" id="km2">1</n>
	</s>
	<s c="ו">
		<n v="ו" id="la">4401</n>
		<n v="וֹ" id="lb">7631</n>
		<n v="וּ" id="lc">23</n>
		<n v="וׄ" id="ld">1</n>
	</s>
	<s c="והי">
		<n v="וּהִי" id="le">1</n>
	</s>
	<s c="וך">
		<n v="וּךְ" id="lf">4</n>
	</s>
	<s c="י">
		<n v="י" id="ma">7013</n>
		<n v="יַ" id="mb">2</n>
	</s>
	<s c="ידע">
		<n v="ידע" id="mc">1</n>
	</s>
	<s c="יה">
		<n v="יָהּ" id="md">1</n>
		<n v="יהָ" id="me">1</n>
	</s>
	<s c="יהם">
		<n v="יהֶם" id="mf">1</n>
	</s>
	<s c="יו">
		<n v="יו" id="mg">4</n>
	</s>
	<s c="יונים">
		<n v="יונים" id="mh">1</n>
	</s>
	<s c="יך">
		<n v="יךְ" id="mi">1</n>
	</s>
	<s c="ינה">
		<n v="ינה" id="mj">1</n>
	</s>
	<s c="ך">
		<n v="ך" id="na">60</n>
		<n v="ךְ" id="nb">1836</n>
		<n v="ךָ" id="nc">6423</n>
		<n v="ךָֽ" id="nd">14</n>
		<n v="ךָּ" id="ne">101</n>
	</s>
	<s c="כה">
		<n v="כֵה" id="nf">1</n>
		<n v="כָה" id="ng">31</n>
		<n v="כָּה" id="nh">7</n>
	</s>
	<s c="כון">
		<n v="כוֹן" id="ni">10</n>
	</s>
	<s c="כי">
		<n v="כִי" id="nj">11</n>
		<n v="כי" id="nk">3</n>
	</s>
	<s c="כם">
		<n v="כֶֽם" id="nl">386</n>
		<n v="כֶם" id="nm">2228</n>
		<n v="כֹם" id="no">5</n>
		<n v="כם" id="np">6</n>
	</s>
	<s c="כן">
		<n v="כֶֽן" id="nq">4</n>
		<n v="כֶן" id="nr">11</n>
	</s>
	<s c="כנה">
		<n v="כֶֽנָה" id="ns">1</n>
		<n v="כֶנָה" id="nt">2</n>
	</s>
	<s c="ם">
		<n v="ם" id="oa">3957</n>
	</s>
	<s c="מו">
		<n v="מו" id="ob">1</n>
		<n v="מוֹ" id="oc">116</n>
		<n v="מוּ" id="od">1</n>
	</s>
	<s c="ן">
		<n v="ן" id="pa">347</n>
	</s>
	<s c="נ">
		<n v="נ" id="pb">1</n>
		<n v="נְ" id="pc">9</n>
		<n v="נֶ" id="pd">2</n>
		<n v="נַ" id="pe">1</n>
	</s>
	<s c="נא">
		<n v="נָא" id="pf">10</n>
		<n v="נא" id="pg">1</n>
	</s>
	<s c="נה">
		<n v="נָה" id="ph">12</n>
		<n v="נָּֽה" id="pi">1</n>
		<n v="נָּה" id="pj">195</n>
		<n v="נה" id="pk">1</n>
	</s>
	<s c="נהו">
		<n v="נְהֽוּ" id="pl">1</n>
		<n v="נְהוּ" id="pm">4</n>
	</s>
	<s c="נו">
		<n v="נּֽוּ" id="pn">3</n>
		<n v="נּוּ" id="po">544</n>
		<n v="נׄוּׄ" id="pp">2</n>
		<n v="נו" id="pq">11</n>
		<n v="נוֹ" id="pr">1</n>
		<n v="נוּ" id="ps">1603</n>
	</s>
	<s c="ני">
		<n v="נִֽי" id="pt">1</n>
		<n v="נִי" id="pu">1192</n>
		<n v="נִּי" id="pv">112</n>
		<n v="ני" id="pw">6</n>
	</s>
	<s c="נך">
		<n v="נְךָּ" id="px">1</n>
	</s>
	<s c="נני">
		<n v="נְנִי" id="py">1</n>
	</s>
</dic>